LICENSE.txt
MANIFEST.in
README.rst
setup.cfg
setup.py
rastools/__init__.py
rastools/csvwrite.py
rastools/data_parsers.py
rastools/data_writers.py
rastools/datparse.py
rastools/datwrite.py
rastools/image_writers.py
rastools/rasdump.py
rastools/rasextract.py
rastools/rasinfo.py
rastools/rasparse.py
rastools/rasutility.py
rastools/rasviewer.py
rastools/raswrite.py
rastools/settings.py
rastools/terminal.py
rastools/tiffwrite.py
rastools/xcfwrite.py
rastools/xlswrite.py
rastools.egg-info/PKG-INFO
rastools.egg-info/SOURCES.txt
rastools.egg-info/dependency_links.txt
rastools.egg-info/entry_points.txt
rastools.egg-info/requires.txt
rastools.egg-info/top_level.txt
rastools.egg-info/zip-safe
rastools/windows/__init__.py
rastools/windows/figure_canvas.py
rastools/windows/main_window.py
rastools/windows/main_window.ui
rastools/windows/multi_layer_window.py
rastools/windows/multi_layer_window.ui
rastools/windows/open_dialog.py
rastools/windows/open_dialog.ui
rastools/windows/progress_dialog.py
rastools/windows/progress_dialog.ui
rastools/windows/single_layer_window.py
rastools/windows/single_layer_window.ui
rastools/windows/sub_window.py
rastools/windows/title_info_dialog.py
rastools/windows/title_info_dialog.ui
rastools/windows/fallback-theme/application-exit.png
rastools/windows/fallback-theme/application-exit.svg
rastools/windows/fallback-theme/document-open.png
rastools/windows/fallback-theme/document-open.svg
rastools/windows/fallback-theme/document-print.png
rastools/windows/fallback-theme/document-print.svg
rastools/windows/fallback-theme/document-save.png
rastools/windows/fallback-theme/document-save.svg
rastools/windows/fallback-theme/home-axes.png
rastools/windows/fallback-theme/home-axes.svg
rastools/windows/fallback-theme/image-x-generic.png
rastools/windows/fallback-theme/image-x-generic.svg
rastools/windows/fallback-theme/pan-mode.png
rastools/windows/fallback-theme/pan-mode.svg
rastools/windows/fallback-theme/reset-axes.png
rastools/windows/fallback-theme/reset-axes.svg
rastools/windows/fallback-theme/text-x-generic.png
rastools/windows/fallback-theme/text-x-generic.svg
rastools/windows/fallback-theme/x-office-document.png
rastools/windows/fallback-theme/x-office-document.svg
