Metadata-Version: 1.1
Name: rastools
Version: 0.5
Summary: Tools for converting SSRL scans into images
Home-page: https://www.waveform.org.uk/rastools/
Author: Dave Hughes
Author-email: dave@waveform.org.uk
License: UNKNOWN
Keywords: science synchrotron
Platform: ALL
Classifier: Development Status :: 4 - Beta
Classifier: Environment :: Console
Classifier: Environment :: Win32 (MS Windows)
Classifier: Environment :: X11 Applications :: Qt
Classifier: Intended Audience :: Science/Research
Classifier: License :: OSI Approved :: GNU General Public License v3 or later (GPLv3+)
Classifier: Operating System :: Microsoft :: Windows
Classifier: Operating System :: POSIX
Classifier: Operating System :: Unix
Classifier: Programming Language :: Python :: 2.6
Classifier: Programming Language :: Python :: 2.7
Classifier: Topic :: Multimedia :: Graphics
Classifier: Topic :: Scientific/Engineering
